autocheck/__init__.py
autocheck/__main__.py
autocheck/autorunner.py
autocheck/colorizer.py
autocheck/compat.py
autocheck/db.py
autocheck/encoding.py
autocheck/filtersuite.py
autocheck/growler.py
autocheck/main.py
autocheck/status.py
autocheck/tagexpression.py
autocheck/tags.py
autocheck/testrunner.py
autocheck/colourschemes/light.yaml
autocheck/contrib/__init__.py
autocheck/contrib/debug/__init__.py
autocheck/contrib/debug/logger.py
autocheck/contrib/debug/tracing.py
autocheck/contrib/django/__init__.py
autocheck/contrib/django/discoveryrunner.py
autocheck/contrib/django/quickstart.py
autocheck/contrib/django/testsuiterunner.py
autocheck/images/fail.png
autocheck/images/pass.png
autocheck/images/pending.png
autocheck-0.2.7.dist-info/DESCRIPTION.rst
autocheck-0.2.7.dist-info/entry_points.txt
autocheck-0.2.7.dist-info/METADATA
autocheck-0.2.7.dist-info/metadata.json
autocheck-0.2.7.dist-info/pbr.json
autocheck-0.2.7.dist-info/RECORD
autocheck-0.2.7.dist-info/top_level.txt
autocheck-0.2.7.dist-info/WHEEL
vows/__init__.py
vows/extra_matchers.py
vows/test_colorizer.py
vows/test_db.py
vows/test_extra_matchers.py
vows/test_filtersuite.py
vows/test_tagexpression.py
vows/test_tags.py
vows/test_testresult.py
vows/test_testrunner.py
