Metadata-Version: 2.0
Name: autocheck
Version: 0.2.7
Summary: Improved unittest test runner
Home-page: https://github.com/htmue/python-autocheck
Author: Hans-Thomas Mueller
Author-email: htmue@mac.com
License: UNLICENSE
Platform: UNKNOWN
Classifier: Development Status :: 4 - Beta
Classifier: Environment :: Console
Classifier: Intended Audience :: Developers
Classifier: License :: Freely Distributable
Classifier: License :: Public Domain
Classifier: Programming Language :: Python :: 2.6
Classifier: Programming Language :: Python :: 2.7
Classifier: Programming Language :: Python :: 3.3
Classifier: Programming Language :: Python :: 3.4
Classifier: Topic :: Software Development :: Testing
Requires-Dist: PyYAML
Requires-Dist: watchdog
Requires-Dist: python-termstyle
Requires-Dist: six
Requires-Dist: unittest2; python_version=="2.6"
Provides-Extra: gntp
Requires-Dist: gntp (>=0.7); extra == 'gntp'
